clophfit/__init__.py
clophfit/__main__.py
clophfit/py.typed
clophfit/types.py
clophfit/binding/__init__.py
clophfit/binding/fitting.py
clophfit/binding/plotting.py
clophfit/old/__init__.py
clophfit/old/dil_buffer.py
clophfit/old/dil_correction.py
clophfit/old/merge.py
clophfit/old/plot_tecan.py
clophfit/old/bash/fit.tecan
clophfit/old/bash/fit.tecan.cl
clophfit/old/bash/new_sort_K.sh
clophfit/old/bash/sum_all
clophfit/old/bash/sum_e2
clophfit/old/bash/sum_lib
clophfit/old/bash/sum_lib2
clophfit/old/bash/sum_s202n
clophfit/old/bash/sum_v224q
clophfit/old/bash/w_ave.sh
clophfit/prenspire/__init__.py
clophfit/prenspire/prenspire.py
clophfit/prtecan/__init__.py
clophfit/prtecan/prtecan.py
clophfit-0.12.0.dist-info/METADATA
clophfit-0.12.0.dist-info/WHEEL
clophfit-0.12.0.dist-info/entry_points.txt
clophfit-0.12.0.dist-info/licenses/LICENSE.txt
clophfit-0.12.0.dist-info/RECORD
