Metadata-Version: 2.3
Name: clophfit
Version: 0.12.0
Summary: Cli for fitting macromolecule pH titration or binding assays data e.g. fluorescence spectra.
Project-URL: Bug Tracker, https://github.com/darosio/ClopHfit/issues
Project-URL: Changelog, https://github.com/darosio/ClopHfit/blob/main/CHANGELOG.md
Project-URL: Documentation, https://clophfit.readthedocs.io
Project-URL: Github releases, https://github.com/darosio/ClopHfit/releases
Project-URL: Homepage, https://github.com/darosio/ClopHfit
Author-email: daniele arosio <daniele.arosio@cnr.it>
License: BSD-3-Clause
Keywords: ClopHensor,data fitting,macromolecule binding,pH,svd
Classifier: Development Status :: 3 - Alpha
Classifier: Environment :: Console
Classifier: Intended Audience :: Science/Research
Classifier: Operating System :: OS Independent
Classifier: Programming Language :: Python :: 3 :: Only
Classifier: Programming Language :: Python :: 3.10
Classifier: Programming Language :: Python :: 3.11
Classifier: Programming Language :: Python :: 3.12
Classifier: Programming Language :: Unix Shell
Classifier: Topic :: Scientific/Engineering
Requires-Python: >=3.10
Requires-Dist: arviz<=0.20.0
Requires-Dist: click<=8.1.7
Requires-Dist: corner<=2.2.3
Requires-Dist: emcee<=3.1.6
Requires-Dist: lmfit<=1.3.2
Requires-Dist: matplotlib<=3.9.3
Requires-Dist: numpy<=2.1.3
Requires-Dist: openpyxl<=3.1.5
Requires-Dist: pandas<=2.2.3
Requires-Dist: pymc<=5.18.2
Requires-Dist: scipy<=1.14.1
Requires-Dist: seaborn<=0.13.2
Requires-Dist: sympy<=1.13.3
Requires-Dist: tqdm<=4.67.1
Requires-Dist: xlrd<=2.0.1
Provides-Extra: dev
Requires-Dist: commitizen<=4.0.0; extra == 'dev'
Requires-Dist: ipykernel; extra == 'dev'
Requires-Dist: jupyter; extra == 'dev'
Requires-Dist: jupyterlab; extra == 'dev'
Requires-Dist: pre-commit<=4.0.1; extra == 'dev'
Requires-Dist: pylsp-mypy; extra == 'dev'
Requires-Dist: ruff-lsp; extra == 'dev'
Requires-Dist: ruff<=0.8.1; extra == 'dev'
Provides-Extra: docs
Requires-Dist: autodocsumm<=0.2.14; extra == 'docs'
Requires-Dist: graphviz; extra == 'docs'
Requires-Dist: nbsphinx<=0.9.5; extra == 'docs'
Requires-Dist: pydata-sphinx-theme<=0.16.0; extra == 'docs'
Requires-Dist: sphinx-autodoc-typehints<=2.5.0; extra == 'docs'
Requires-Dist: sphinx-click<=6.0.0; extra == 'docs'
Requires-Dist: sphinx<=8.1.3; extra == 'docs'
Requires-Dist: sphinxcontrib-plantuml<=0.30; extra == 'docs'
Provides-Extra: tests
Requires-Dist: coverage[toml]<=7.6.8; extra == 'tests'
Requires-Dist: mypy<=1.13.0; extra == 'tests'
Requires-Dist: pandas-stubs<=2.2.3.241126; extra == 'tests'
Requires-Dist: pygments<=2.18.0; extra == 'tests'
Requires-Dist: pytest<=8.3.4; extra == 'tests'
Requires-Dist: types-click<=7.1.8; extra == 'tests'
Requires-Dist: types-setuptools<=75.6.0.20241126; extra == 'tests'
Requires-Dist: xdoctest<=1.2.0; extra == 'tests'
